CHANGELOG.md
MANIFEST.in
README.md
__init__.py
requirements-test.txt
requirements.txt
setup.cfg
setup.py
ajax_select/LICENSE.txt
ajax_select/__init__.py
ajax_select/admin.py
ajax_select/apps.py
ajax_select/fields.py
ajax_select/helpers.py
ajax_select/lookup_channel.py
ajax_select/registry.py
ajax_select/urls.py
ajax_select/views.py
ajax_select/static/ajax_select/css/ajax_select.css
ajax_select/static/ajax_select/css/jquery-ui.css
ajax_select/static/ajax_select/css/jquery-ui.min.css
ajax_select/static/ajax_select/css/jquery-ui.structure.css
ajax_select/static/ajax_select/css/jquery-ui.structure.min.css
ajax_select/static/ajax_select/css/jquery-ui.theme.css
ajax_select/static/ajax_select/css/jquery-ui.theme.min.css
ajax_select/static/ajax_select/css/images/ui-bg_glass_55_fbf9ee_1x400.png
ajax_select/static/ajax_select/css/images/ui-bg_glass_65_ffffff_1x400.png
ajax_select/static/ajax_select/css/images/ui-bg_glass_75_dadada_1x400.png
ajax_select/static/ajax_select/css/images/ui-bg_glass_75_e6e6e6_1x400.png
ajax_select/static/ajax_select/css/images/ui-bg_glass_95_fef1ec_1x400.png
ajax_select/static/ajax_select/css/images/ui-bg_highlight-soft_75_cccccc_1x100.png
ajax_select/static/ajax_select/css/images/ui-icons_222222_256x240.png
ajax_select/static/ajax_select/css/images/ui-icons_2e83ff_256x240.png
ajax_select/static/ajax_select/css/images/ui-icons_454545_256x240.png
ajax_select/static/ajax_select/css/images/ui-icons_888888_256x240.png
ajax_select/static/ajax_select/css/images/ui-icons_cd0a0a_256x240.png
ajax_select/static/ajax_select/images/loading-indicator.gif
ajax_select/static/ajax_select/js/ajax_select.js
ajax_select/static/ajax_select/js/bootstrap.js
ajax_select/static/ajax_select/js/jquery-ui.js
ajax_select/static/ajax_select/js/jquery-ui.min.js
ajax_select/templates/ajax_select/autocomplete.html
ajax_select/templates/ajax_select/autocompleteselect.html
ajax_select/templates/ajax_select/autocompleteselectmultiple.html
django_ajax_selects_xadmin.egg-info/PKG-INFO
django_ajax_selects_xadmin.egg-info/SOURCES.txt
django_ajax_selects_xadmin.egg-info/dependency_links.txt
django_ajax_selects_xadmin.egg-info/not-zip-safe
django_ajax_selects_xadmin.egg-info/top_level.txt
tests/__init__.py
tests/admin.py
