Metadata-Version: 1.1
Name: django-ajax-selects-xadmin
Version: 1.7.1
Summary: Edit ForeignKey, ManyToManyField and CharField in Django Admin using jQuery UI AutoComplete.
Home-page: https://github.com/1FENQI/django-ajax-selects.git
Author: 1FENQI
Author-email: eddiep@1fenqi.com
License: MIT
Platform: UNKNOWN
Classifier: Programming Language :: Python
Classifier: Programming Language :: Python :: 2
Classifier: Programming Language :: Python :: 3
Classifier: Development Status :: 5 - Production/Stable
Classifier: Environment :: Web Environment
Classifier: Intended Audience :: Developers
Classifier: License :: OSI Approved :: MIT License
Classifier: Operating System :: OS Independent
Classifier: Topic :: Software Development :: Libraries :: Python Modules
Classifier: Topic :: Software Development :: User Interfaces
Classifier: Framework :: Django
